addax/__init__.py
addax/addax.py
addax-1.0.0.dist-info/LICENSE
addax-1.0.0.dist-info/METADATA
addax-1.0.0.dist-info/WHEEL
addax-1.0.0.dist-info/RECORD
