Metadata-Version: 2.3
Name: addax
Version: 1.0.0
Summary: Text analysis library
License: MIT
Author: Dalia Tavizon-Dykstra
Requires-Python: >=3.12,<4.0
Classifier: License :: OSI Approved :: MIT License
Classifier: Programming Language :: Python :: 3
Classifier: Programming Language :: Python :: 3.12
Classifier: Programming Language :: Python :: 3.13
Requires-Dist: pandas (>=2.2.3,<3.0.0)
Requires-Dist: textblob (>=0.19.0,<0.20.0)
